bletl/__init__.py
bletl/core.py
bletl/features.py
bletl/growth.py
bletl/heuristics.py
bletl/py.typed
bletl/splines.py
bletl/types.py
bletl/utils.py
bletl/parsing/__init__.py
bletl/parsing/bl1.py
bletl/parsing/blpro.py
bletl-1.6.1.dist-info/licenses/LICENSE.md
bletl-1.6.1.dist-info/METADATA
bletl-1.6.1.dist-info/WHEEL
bletl-1.6.1.dist-info/top_level.txt
bletl-1.6.1.dist-info/RECORD
