Metadata-Version: 2.4
Name: bletl
Version: 1.6.1
Summary: Package for parsing and transforming BioLector raw data.
Author-email: Michael Osthege <m.osthege@fz-juelich.de>
License: GNU Affero General Public License v3
Project-URL: Homepage, https://github.com/jubiotech/bletl
Project-URL: Documentation, https://bletl.readthedocs.io/en/latest/
Project-URL: Download, https://pypi.org/project/bletl/
Classifier: Programming Language :: Python
Classifier: Operating System :: OS Independent
Classifier: Programming Language :: Python :: 3.8
Classifier: Programming Language :: Python :: 3.9
Classifier: Programming Language :: Python :: 3.10
Classifier: Programming Language :: Python :: 3.11
Classifier: Intended Audience :: Science/Research
Classifier: License :: OSI Approved :: GNU Affero General Public License v3
Requires-Python: >=3.8
License-File: LICENSE.md
Requires-Dist: csaps>=0.11
Requires-Dist: fastprogress
Requires-Dist: joblib
Requires-Dist: numpy
Requires-Dist: pandas
Requires-Dist: scipy
Requires-Dist: tsfresh
Requires-Dist: setuptools
Dynamic: license-file
